{"image_dims": "[2347, 1667, 1]", "Fields": [{"key": {"tag": "Invoice Number", "bbox": {"xmin": 861, "ymin": 145, "xmax": 986, "ymax": 171}}, "value": {"label": "Invoice_number", "tag": "VC 3847/A-G", "bbox": {"xmin": 866, "ymin": 162, "xmax": 1028, "ymax": 209}}}, {"key": {"tag": "Invoice Date (tax point)", "bbox": {"xmin": 865, "ymin": 205, "xmax": 1033, "ymax": 224}}, "value": {"label": "Invoice_date", "tag": "20/07/2000", "bbox": {"xmin": 870, "ymin": 216, "xmax": 1005, "ymax": 255}}}, {"key": {"tag": "Invoice Total", "bbox": {"xmin": 1190, "ymin": 1534, "xmax": 1293, "ymax": 1556}}, "value": {"label": "total_amount", "tag": "240000.00", "bbox": {"xmin": 1366, "ymin": 1541, "xmax": 1489, "ymax": 1578}}}]}