{"image_dims": "[2112, 1692, 1]", "Fields": [{"key": {"tag": "PO #:", "bbox": {"xmin": 982, "ymin": 514, "xmax": 1067, "ymax": 548}}, "value": {"label": "Purchase_order", "tag": "20026", "bbox": {"xmin": 1079, "ymin": 518, "xmax": 1165, "ymax": 539}}}, {"key": {"tag": "Date:", "bbox": {"xmin": 975, "ymin": 191, "xmax": 1046, "ymax": 224}}, "value": {"label": "Invoice_date", "tag": "9/27/01", "bbox": {"xmin": 1074, "ymin": 190, "xmax": 1174, "ymax": 217}}}, {"key": {"tag": "Invoice #:", "bbox": {"xmin": 926, "ymin": 228, "xmax": 1055, "ymax": 266}}, "value": {"label": "Invoice_number", "tag": "PR09011327", "bbox": {"xmin": 1075, "ymin": 229, "xmax": 1267, "ymax": 260}}}, {"key": {"tag": "Total", "bbox": {"xmin": 1022, "ymin": 1138, "xmax": 1103, "ymax": 1164}}, "value": {"label": "total_amount", "tag": "$7,464.44", "bbox": {"xmin": 1217, "ymin": 1147, "xmax": 1340, "ymax": 1166}}}]}