{"image_dims": "[2245, 1692, 1]", "Fields": [{"key": {"tag": "date", "bbox": {"xmin": 116, "ymin": 218, "xmax": 221, "ymax": 255}}, "value": {"label": "Invoice_date", "tag": "06/29/98", "bbox": {"xmin": 98, "ymin": 296, "xmax": 258, "ymax": 327}}}, {"key": {"tag": "invoice no.", "bbox": {"xmin": 293, "ymin": 209, "xmax": 470, "ymax": 260}}, "value": {"label": "Invoice_number", "tag": "RQ8708", "bbox": {"xmin": 290, "ymin": 297, "xmax": 412, "ymax": 323}}}, {"key": {"tag": "total", "bbox": {"xmin": 1116, "ymin": 723, "xmax": 1240, "ymax": 776}}, "value": {"label": "total_amount", "tag": "104.10", "bbox": {"xmin": 1386, "ymin": 730, "xmax": 1505, "ymax": 762}}}]}